arvan/__init__.py
arvan/client.py
arvan-0.1.1.dist-info/METADATA
arvan-0.1.1.dist-info/WHEEL
arvan-0.1.1.dist-info/top_level.txt
arvan-0.1.1.dist-info/RECORD
