Metadata-Version: 2.1
Name: arvan
Version: 0.1.1
Summary: Arvan is python api to work with arvancloud
Home-page: https://github.com/silkenpy/arvan
Author: silkenpy
Author-email: silkenpy@gmail.com
License: UNKNOWN
Platform: UNKNOWN
Classifier: Programming Language :: Python :: 3
Classifier: License :: OSI Approved :: MIT License
Classifier: Operating System :: OS Independent
Requires-Python: >=3.6
Requires-Dist: requests
